cryptocom/__init__.py
cryptocom/ccxt/__init__.py
cryptocom/ccxt/cryptocom.py
cryptocom/ccxt/abstract/cryptocom.py
cryptocom/ccxt/async_support/__init__.py
cryptocom/ccxt/async_support/cryptocom.py
cryptocom/ccxt/async_support/base/__init__.py
cryptocom/ccxt/async_support/base/exchange.py
cryptocom/ccxt/async_support/base/throttler.py
cryptocom/ccxt/async_support/base/ws/__init__.py
cryptocom/ccxt/async_support/base/ws/cache.py
cryptocom/ccxt/async_support/base/ws/client.py
cryptocom/ccxt/async_support/base/ws/functions.py
cryptocom/ccxt/async_support/base/ws/future.py
cryptocom/ccxt/async_support/base/ws/order_book.py
cryptocom/ccxt/async_support/base/ws/order_book_side.py
cryptocom/ccxt/base/__init__.py
cryptocom/ccxt/base/decimal_to_precision.py
cryptocom/ccxt/base/errors.py
cryptocom/ccxt/base/exchange.py
cryptocom/ccxt/base/precise.py
cryptocom/ccxt/base/types.py
cryptocom/ccxt/pro/__init__.py
cryptocom/ccxt/pro/cryptocom.py
cryptocom/ccxt/static_dependencies/README.md
cryptocom/ccxt/static_dependencies/__init__.py
cryptocom/ccxt/static_dependencies/bip/__init__.py
cryptocom/ccxt/static_dependencies/bip/addr/P2PKH_addr.py
cryptocom/ccxt/static_dependencies/bip/addr/__init__.py
cryptocom/ccxt/static_dependencies/bip/addr/addr_dec_utils.py
cryptocom/ccxt/static_dependencies/bip/addr/addr_key_validator.py
cryptocom/ccxt/static_dependencies/bip/addr/iaddr_decoder.py
cryptocom/ccxt/static_dependencies/bip/addr/iaddr_encoder.py
cryptocom/ccxt/static_dependencies/bip/base58/__init__.py
cryptocom/ccxt/static_dependencies/bip/base58/base58.py
cryptocom/ccxt/static_dependencies/bip/base58/base58_ex.py
cryptocom/ccxt/static_dependencies/bip/base58/base58_xmr.py
cryptocom/ccxt/static_dependencies/bip/bech32/__init__.py
cryptocom/ccxt/static_dependencies/bip/bech32/bch_bech32.py
cryptocom/ccxt/static_dependencies/bip/bech32/bech32.py
cryptocom/ccxt/static_dependencies/bip/bech32/bech32_base.py
cryptocom/ccxt/static_dependencies/bip/bech32/bech32_ex.py
crypto_com_sdk-0.0.119.dist-info/METADATA
crypto_com_sdk-0.0.119.dist-info/WHEEL
crypto_com_sdk-0.0.119.dist-info/RECORD
